qpsk_mod/__init__.py
qpsk_mod/main.py
qpsk_mod-0.1.0.dist-info/METADATA
qpsk_mod-0.1.0.dist-info/WHEEL
qpsk_mod-0.1.0.dist-info/top_level.txt
qpsk_mod-0.1.0.dist-info/RECORD
